PMAR_Breakdowns.py
PMAR_Breakdowns-1.10.dist-info/METADATA
PMAR_Breakdowns-1.10.dist-info/WHEEL
PMAR_Breakdowns-1.10.dist-info/top_level.txt
PMAR_Breakdowns-1.10.dist-info/RECORD
